zhaomath/__init__.py
zhaomath/module_a1.py
zhaomath/module_a2.py
zhaomath-1.0.dist-info/METADATA
zhaomath-1.0.dist-info/WHEEL
zhaomath-1.0.dist-info/top_level.txt
zhaomath-1.0.dist-info/RECORD
