Metadata-Version: 2.1
Name: zhaomath
Version: 1.0
Summary: 自定义函数
Author: zhao
Author-email: zhao@163.com
License: UNKNOWN
Platform: UNKNOWN
